.coverage
.gitignore
.travis.yml
LICENSE
MANIFEST.in
requirements.txt
setup.py
jetway/VERSION
jetway/__init__.py
jetway/__init__.pyc
jetway/jetway.py
jetway/jetway.pyc
jetway/jetway_test.py
jetway/jetway_test.pyc
jetway.egg-info/PKG-INFO
jetway.egg-info/SOURCES.txt
jetway.egg-info/dependency_links.txt
jetway.egg-info/requires.txt
jetway.egg-info/top_level.txt
jetway/testdata/build/file.txt
jetway/testdata/build/index.html