Metadata-Version: 1.1
Name: jetway
Version: 0.0.512
Summary: Client library for the Jetway static site staging service.
Home-page: https://github.com/grow/jetway-client
Author: Grow SDK Authors
Author-email: hello@grow.io
License: MIT
Keywords: grow,cms,static site generator,s3,google cloud storage,content management
Platform: UNKNOWN
Classifier: Development Status :: 2 - Pre-Alpha
Classifier: Environment :: Web Environment
Classifier: Intended Audience :: Developers
Classifier: License :: OSI Approved :: MIT License
Classifier: Natural Language :: English
Classifier: Operating System :: OS Independent
Classifier: Programming Language :: Python :: 2.7
Classifier: Programming Language :: Python
Classifier: Topic :: Internet :: WWW/HTTP :: Dynamic Content
Classifier: Topic :: Internet :: WWW/HTTP
Classifier: Topic :: Software Development :: Libraries :: Python Modules
